datalabutils/DataMaker.py
datalabutils/__init__.py
datalabutils/datalabutils.py
datalabutils/photoz_utils.py
astrodatautils-0.1.0.dist-info/AUTHORS.rst
astrodatautils-0.1.0.dist-info/METADATA
astrodatautils-0.1.0.dist-info/WHEEL
astrodatautils-0.1.0.dist-info/top_level.txt
astrodatautils-0.1.0.dist-info/RECORD
